tenon/__init__.py
tenon/detect.py
tenon-0.1.7.dist-info/LICENSE
tenon-0.1.7.dist-info/METADATA
tenon-0.1.7.dist-info/WHEEL
tenon-0.1.7.dist-info/top_level.txt
tenon-0.1.7.dist-info/RECORD
