Metadata-Version: 2.1
Name: tenon
Version: 0.1.7
Summary: A package to solve captcha
Home-page: https://github.com/Juannie-PP/tenon
Author: Juannie-PP
Author-email: 2604868278@qq.com
License: MIT
Keywords: rotate_captcha,notch_captcha,captcha identify,captcha,verification code
Classifier: Programming Language :: Python :: 3
Requires-Python: >=3.7
License-File: LICENSE
Requires-Dist: requests (>=2.19.1)
Requires-Dist: numpy (>=1.21.5)
Requires-Dist: opencv-python (==4.5.5.64)
